Workbook

Sheet README
A1: CTDAM-CEMAC — Base de données de la plateforme
A3: Feuille | B3: Contenu | C3: Alimente l'onglet
A4: EMISSIONS | B4: Tableau de suivi des émissions (adjudications) | C4: Accueil, Statistiques, Données hist.
A5: REMBOURSEMENTS | B5: Suivi des coupon + remboursements principal | C5: Tombée des échéances, Statistiques
A6: SVT | B6: Spécialistes en Valeurs du Trésor | C6: Bottin, Accueil
A7: SGP | B7: Sociétés de Gestion et de Portefeuille | C7: Bottin
A8: SDB | B8: Sociétés de Bourse | C8: Bottin
A9: INVESTISSEURS_INST | B9: Investisseurs institutionnels enregistrés | C9: Bottin
A10: UTILISATEURS | B10: Comptes plateforme (statut, profil) | C10: Admin
A11: PAYS_MACRO | B11: PIB, dette, inflation, solde budgétaire par pays/an | C11: Macro, Statistiques
A12: ENCOURS_MENSUEL | B12: Encours OTA+BTA par pays et mois | C12: Accueil, Statistiques
A13: CALENDRIER_EMISSIONS | B13: Prévisionnel des futures émissions | C13: Calendrier
A14: COURBE_TAUX | B14: Courbe des taux par maturité et date | C14: Statistiques, Calculs
... A19: PARAMETRES | B19: Paramètres globaux de la plateforme | C19: Système

Sheet EMISSIONS
A1: TABLEAU DE SUIVI DES ÉMISSIONS — CTDAM-CEMAC
A2: Code Long | B2: Code Court | C2: Pays | D2: Instrument | E2: Maturité | F2: Montant (millions de FCFA) | G2: Date d'adjudication | H2: Date de remboursement | I2: SVT Locaux | J2: SVT Déplacés | K2: Montant levé | L2: Nb SVT Émetteurs | M2: Nb SVT Participés | N2: Taux Participation (%) | O2: TRMP (%) | P2: Taux Souscription (%) | Q2: Taux Limite (%) | R2: Min BTA/OTA (%) | S2: Max BTA/OTA (%) | T2: Rendement | U2: Taux Facial (%) | V2: Taux Couverture | W2: Nature de l opération
A3: Code Long | B3: Code Court | C3: Pays | D3: Instrument | E3: Maturité | F3: Montant Émis (M XAF) | G3: Jour Souscription | H3: Date Remboursement | I3: SVT Locaux (M) | J3: SVT Déplacés (M) | K3: Montant Levé (M) | L3: Nb SVT Émetteurs | M3: Nb SVT Participés | N3: Taux Participation (%) | O3: TRMP (%) | P3: Taux Souscription (%) | Q3: Taux Limite (%) | R3: Min BTA/OTA (%) | S3: Max BTA/OTA (%) | T3: PMP / Rendement (%) | U3: Taux Facial (%) | V3: Taux Couverture | W3: Statut
A4: CM2A00000014 OTA 2 ANS 4% 08-JUIN -2015 | B4: =MID(A4,1,12) -> CM2A00000014 | C4: Cameroun | D4: OTA | E4: 2 ANS | F4: 16000 | G4: 41430 | H4: 42163 | I4: 16000 | K4: 16000 | N4: 0 | O4: 100.38 | P4: 87.29 | Q4: 100 | T4: 3.9842249 | U4: 4 | W4: émission
A5: GA2J00000015 OTA 3 ANS 4,5% 02-AOUT -2016 | B5: =MID(A5,1,12) -> GA2J00000015 | C5: Gabon | D5: OTA | E5: 3 ANS | F5: 25500 | G5: 41486 | H5: 42584 | I5: 20000 | J5: 5500 | K5: 25500 | N5: 0 | O5: 99.92 | P5: 36.4 | Q5: 98.5 | T5: 4.5036246 | U5: 4.5 | W5: émission
A6: CM2A00000023 OTA 2 ANS 4% 07-SEPT -2015 | B6: =MID(A6,1,12) -> CM2A00000023 | C6: Cameroun | D6: OTA | E6: 2 ANS | F6: 7511 | G6: 41521 | H6: 42254 | I6: 6011 | J6: 1500 | K6: 7511 | N6: 0 | O6: 98.5 | P6: 80.11 | Q6: 97 | T6: 4.0634252 | U6: 4 | W6: émission
A7: CM2A00000032 OTA 2 ANS 3,75% 08-AOUT -2016 | B7: =MID(A7,1,12) -> CM2A00000032 | C7: Cameroun | D7: OTA | E7: 2 ANS | F7: 10000 | G7: 41857 | H7: 42590 | I7: 7305 | J7: 2695 | K7: 10000 | N7: 0 | O7: 100.05 | P7: 191.55 | Q7: 100 | T7: 3.748039 | U7: 3.75 | W7: émission
A8: GA2J00000024 OTA 3 ANS 5,30% 26-SEPT -2017 | B8: =MID(A8,1,12) -> GA2J00000024 | C8: Gabon | D8: OTA | E8: 3 ANS | F8: 26050 | G8: 41906 | H8: 43004 | K8: 0 | N8: 0 | O8: 98.89 | P8: 74.4 | T8: 7970.4621 | U8: 7881.99 | W8: émission
A9: GA2J00000042 OTA 3 ANS 5,3% 12-DECE -2017 | B9: =MID(A9,1,12) -> GA2J00000042 | C9: Gabon | D9: OTA | E9: 3 ANS | F9: 11006 | G9: 41983 | H9: 43081 | K9: 0 | N9: 0 | O9: 96.88 | P9: 31.45 | T9: 5.471338 | U9: 5.3 | W9: émission
A10: GA2J00000051 OTA 3 ANS 5,3% 10-AVRI -2018 | B10: =MID(A10,1,12) -> GA2J00000051 | C10: Gabon | D10: OTA | E10: 3 ANS | F10: 12500 | G10: 42102 | H10: 43200 | K10: 0 | N10: 0 | O10: 98.23 | P10: 83.33 | T10: 5.3958734 | U10: 5.3 | W10: émission
A11: TD2A00000016 OTA 2 ANS 4,15% 24-JUIL -2017 | B11: =MID(A11,1,12) -> TD2A00000016 | C11: Tchad | D11: OTA | E11: 2 ANS | F11: 2000 | G11: 42207 | H11: 42940 | I11: 2000 | J11: 0 | K11: 2000 | N11: 0 | O11: 97.775 | P11: 6.66666 | Q11: 94.4 | R11: 96.4 | S11: 98.4 | T11: 4.2480809 | U11: 4.15 | W11: émission
A12: TD2A00000016 OTA 2 ANS 4,15% 24-JUIL -2017 | B12: =MID(A12,1,12) -> TD2A00000016 | C12: Tchad | D12: OTA | E12: 2 ANS | F12: 23500 | G12: 42214 | H12: 42940 | K12: 0 | N12: 0 | O12: 96.31 | P12: 78.33 | T12: 4.3150692 | U12: 4.15 | W12: émission
A13: TD2B00000023 OTA 5 ANS 4,15% 21-AOUT -2020 | B13: =MID(A13,1,12) -> TD2B00000023 | C13: Tchad | D13: OTA | E13: 5 ANS | F13: 48760 | G13: 42235 | H13: 44064 | K13: 7050 | N13: 0 | O13: 94.23 | P13: 97.52 | T13: 4.4041761 | U13: 4.15 | W13: émission
A14: TD2B00000041 OTA 5 ANS 4,1% 25-SEPT -2020 | B14: =MID(A14,1,12) -> TD2B00000041 | C14: Tchad | D14: OTA | E14: 5 ANS | F14: 10000 | G14: 42270 | H14: 44099 | J14: 10000 | K14: 10000 | N14: 0 | O14: 100 | P14: 40 | T14: 4.1 | U14: 4.1 | W14: émission
A15: TD2B00000051 OTA 5 ANS 4,1% 02-OCTO -2020 | B15: =MID(A15,1,12) -> TD2B00000051 | C15: Tchad | D15: OTA | E15: 5 ANS | F15: 10000 | G15: 42277 | H15: 44106 | J15: 10000 | K15: 10000 | N15: 0 | O15: 100 | P15: 40 | T15: 4.1 | U15: 4.1 | W15: émission
A16: TD2B00000069 OTA 5 ANS 4,1% 30-OCTO -2020 | B16: =MID(A16,1,12) -> TD2B00000069 | C16: Tchad | D16: OTA | E16: 5 ANS | F16: 15000 | G16: 42305 | H16: 44134 | J16: 15000 | K16: 15000 | N16: 0 | O16: 100 | P16: 100 | T16: 4.1 | U16: 4.1 | W16: émission
A17: GA2A00000014 OTA 2 ANS 4,5% 27-NOVE -2017 | B17: =MID(A17,1,12) -> GA2A00000014 | C17: Gabon | D17: OTA | E17: 2 ANS | F17: 5000 | G17: 42333 | H17: 43066 | I17: 2000 | J17: 3000 | K17: 5000 | N17: 0 | O17: 99.2 | P17: 100 | T17: 4.5375239 | U17: 4.5 | W17: émission
A18: TD2J00000017 OTA 3 ANS 4,1% 02-JANV -2019 | B18: =MID(A18,1,12) -> TD2J00000017 | C18: Tchad | D18: OTA | E18: 3 ANS | F18: 30000 | G18: 42368 | H18: 43467 | I18: 30000 | J18: 0 | K18: 30000 | N18: 0 | O18: 100 | P18: 100 | T18: 4.1 | U18: 4.1 | W18: émission
A19: TD2A00000025 OTA 2 ANS 4% 19-MARS -2018 | B19: =MID(A19,1,12) -> TD2A00000025 | C19: Tchad | D19: OTA | E19: 2 ANS | F19: 35000 | G19: 42445 | H19: 43178 | J19: 0 | K19: 17000 | N19: 0 | O19: 100 | P19: 100 | Q19: 100 | R19: 100 | S19: 100 | T19: 4 | U19: 4 | W19: émission
A20: GA2A00000023 OTA 2 ANS 4,5% 26-MARS -2018 | B20: =MID(A20,1,12) -> GA2A00000023 | C20: Gabon | D20: OTA | E20: 2 ANS | F20: 1300 | G20: 42452 | H20: 43185 | I20: 1000 | J20: 300 | K20: 1300 | N20: 0 | O20: 95 | P20: 18.57 | T20: 4.7446456 | U20: 4.5 | W20: émission
A21: TD2K00000015 OTA 4 ANS 4% 25-MARS -2020 | B21: =MID(A21,1,12) -> TD2K00000015 | C21: Tchad | D21: OTA | E21: 4 ANS | F21: 30000 | G21: 42452 | H21: 43915 | I21: 15300 | J21: 14700 | K21: 30000 | N21: 0 | O21: 98 | P21: 102 | T21: 4.0817578 | W21: émission
A22: TD2A00000043 OTA 2 ANS 3,5% 21-MAI -2018 | B22: =MID(A22,1,12) -> TD2A00000043 | C22: Tchad | D22: OTA | E22: 2 ANS | F22: 25000 | G22: 42508 | H22: 43241 | I22: 20000 | J22: 5000 | K22: 25000 | N22: 0 | O22: 99 | P22: 100 | T22: 3.5371778 | U22: 3.5 | W22: émission
A23: TD2A00000052 OTA 2 ANS 4,00% 28-MAI -2018 | B23: =MID(A23,1,12) -> TD2A00000052 | C23: Tchad | D23: OTA | E23: 2 ANS | F23: 10200 | G23: 42515 | H23: 43248 | I23: 0 | J23: 10200 | K23: 10200 | N23: 0 | O23: 100 | P23: 100 | T23: 4 | U23: 4 | W23: émission
A24: TD2A00000061 OTA 2 ANS 3,5% 25-JUIN -2018 | B24: =MID(A24,1,12) -> TD2A00000061 | C24: Tchad | D24: OTA | E24: 2 ANS | F24: 40157 | G24: 42543 | H24: 43276 | I24: 10157 | J24: 30000 | K24: 40157 | N24: 0 | O24: 100 | P24: 100 | T24: 3.5 | U24: 3.5 | W24: émission
A25: GA2A00000023 OTA 2 ANS 4,5% 26-MARS -2018 | B25: =MID(A25,1,12) -> GA2A00000023 | C25: Gabon | D25: OTA | E25: 2 ANS | F25: 4000 | G25: 42571 | H25: 43185 | I25: 4000 | J25: 0 | K25: 4000 | N25: 0 | O25: 96 | P25: 80 | T25: 4.6937247 | U25: 4.5 | W25: émission
A26: TD2J00000026 OTA 3 ANS 4% 09-SEPT -2019 | B26: =MID(A26,1,12) -> TD2J00000026 | C26: Tchad | D26: OTA | E26: 3 ANS | F26: 5000 | G26: 42620 | H26: 43717 | I26: 5000 | J26: 0 | K26: 5000 | N26: 0 | O26: 99 | P26: 100 | T26: 4.0407252 | U26: 4 | W26: émission
A27: TD2A00000383 OTA 2 ANS 5% 01-OCTO -2018 | B27: =MID(A27,1,12) -> TD2A00000383 | C27: Tchad | D27: OTA | E27: 2 ANS | F27: 5000 | G27: 42641 | H27: 43374 | J27: 5000 | K27: 5000 | N27: 0 | O27: 100 | P27: 100 | T27: 5 | U27: 5 | W27: émission
A28: TD2A00000392 OTA 2 ANS 5% 22-OCTO -2018 | B28: =MID(A28,1,12) -> TD2A00000392 | C28: Tchad | D28: OTA | E28: 2 ANS | F28: 9000 | G28: 42662 | H28: 43395 | I28: 9000 | J28: 0 | K28: 9000 | N28: 0 | O28: 100 | P28: 100 | T28: 5 | U28: 5 | W28: émission
A29: GA2A00000032 OTA 2 ANS 4,75% 26-NOVE -2018 | B29: =MID(A29,1,12) -> GA2A00000032 | C29: Gabon | D29: OTA | E29: 2 ANS | F29: 5000 | G29: 42697 | H29: 43430 | I29: 5000 | J29: 0 | K29: 5000 | N29: 0 | O29: 99.51 | P29: 250 | T29: 4.7741165 | U29: 4.75 | W29: émission
A30: GA2A00000032 OTA 2 ANS 4,75% 26-NOVE -2018#1 | B30: =MID(A30,1,12) -> GA2A00000032 | C30: Gabon | D30: OTA | E30: 2 ANS | F30: 10000 | G30: 42718.716 | H30: 43430 | I30: 5000 | J30: 5000 | K30: 10000 | N30: 0 | O30: 98.62 | P30: 100 | T30: 4.8185195 | U30: 4.75 | W30: émission
A31: TD2A00000409 OTA 2 ANS 4,5% 31-DECE -2018 | B31: =MID(A31,1,12) -> TD2A00000409 | C31: Tchad | D31: OTA | E31: 2 ANS | F31: 15000 | G31: 42732 | H31: 43465 | I31: 15000 | J31: 0 | K31: 15000 | N31: 0 | O31: 99 | P31: 60 | T31: 4.5469974 | U31: 4.5 | W31: émission
A32: GQ2B00000014 OTA 5 ANS 5% 31-MARS -2022 | B32: =MID(A32,1,12) -> GQ2B00000014 | C32: Guinée Equatoriale | D32: OTA | E32: 5 ANS | F32: Annulée | G32: 42823 | H32: Annulée | N32: 0 | O32: Annulée | P32: #VALUE! | T32: #VALUE! | U32: Annulée | W32: émission
A33: TD2A00000418 OTA 2 ANS 4,5% 10-JUIN -2019 | B33: =MID(A33,1,12) -> TD2A00000418 | C33: Tchad | D33: OTA | E33: 2 ANS | F33: 26800 | G33: 42893 | H33: 43626 | I33: 26800 | J33: 0 | K33: 26800 | N33: 0 | O33: 100 | P33: 89.33 | Q33: 100 | R33: 100 | S33: 100 | T33: 4.5 | U33: 4.5 | W33: émission
A34: GA2A00000041 OTA 2 ANS 4,5% 23-SEPT -2019 | B34: =MID(A34,1,12) -> GA2A00000041 | C34: Gabon | D34: OTA | E34: 2 ANS | F34: 8000 | G34: 42998 | H34: 43731 | I34: 0 | J34: 8000 | K34: 8000 | N34: 22.222222 | O34: 99.38 | P34: 20 | Q34: 95 | R34: 95 | S34: 100 | T34: 4.5290296 | U34: 4.5 | W34: émission
A35: GA2A00000051 OTA 2 ANS 4,5% 23-MARS-2020 | B35: =MID(A35,1,12) -> GA2A00000051 | C35: Gabon | D35: OTA | E35: 2 ANS | F35: 7500 | G35: 43180 | H35: 43913 | I35: 7500 | J35: 0 | K35: 7500 | N35: 11.111111 | O35: 97.8867 | P35: 100 | T35: 4.6004225 | U35: 4.5 | W35: émission
A36: GA2A00000051 OTA 2 ANS 4,5% 23-MARS-2020#1 | B36: =MID(A36,1,12) -> GA2A00000051 | C36: Gabon | D36: OTA | E36: 2 ANS | F36: 4100 | G36: 43194 | H36: 43913 | I36: 3995.84 | J36: 104.16 | K36: 4100 | N36: 16.666667 | O36: 96.0832 | P36: 27.3611 | T36: 4.6895348 | U36: 4.5 | W36: émission
A37: GA2A00000069 OTA 2 ANS 5% 25-MAI-2020 | B37: =MID(A37,1,12) -> GA2A00000069 | C37: Gabon | D37: OTA | E37: 2 ANS | F37: 27449 | G37: 43243 | H37: 43976 | I37: 12000 | J37: 15449 | K37: 27449 | N37: 22.222222 | O37: 99.9746 | P37: 78.425 | T37: 5.0013066 | U37: 5 | W37: émission
A38: GA2J00000069 OTA 3 ANS 5,75% 05-JUIL-2021 | B38: =MID(A38,1,12) -> GA2J00000069 | C38: Gabon | D38: OTA | E38: 3 ANS | F38: 8800 | G38: 43285 | H38: 44382 | I38: 2100 | J38: 6700 | K38: 8800 | N38: 16.666667 | O38: 88.2443 | P38: 80.25 | T38: 6.5180499 | U38: 5.75 | W38: émission
A39: GA2J00000069 OTA 3 ANS 5,75% 05-JUIL-2021#1 | B39: =MID(A39,1,12) -> GA2J00000069 | C39: Gabon | D39: OTA | E39: 3 ANS | F39: 5000 | G39: 43313 | H39: 44382 | I39: 0 | J39: 5000 | K39: 5000 | N39: 11.111111 | O39: 75.4411 | P39: 66.6667 | T39: 7.6257142 | U39: 5.75 | W39: émission
A40: GA2B00000026 | B40: =MID(A40,1,12) -> GA2B00000026 | C40: Gabon | D40: OTA | E40: 5 ANS | F40: 10000 | G40: 43313 | H40: 45141 | I40: 0 | J40: 10000 | K40: 10000 | N40: 5.5555556 | O40: 100 | P40: 100 | Q40: 100 | R40: 100 | S40: 100 | T40: 7 | U40: 7 | W40: émission
A41: GA2A00000041 OTA 2 ANS 4,5% 23-SEPT -2019 | B41: =MID(A41,1,12) -> GA2A00000041 | C41: Gabon | D41: OTA | E41: 2 ANS | F41: 18600 | G41: 43355 | H41: 43731 | I41: 11100 | J41: 7500 | K41: 18600 | N41: 0 | O41: 96.1648 | P41: 93 | Q41: 75 | R41: 75 | S41: 100 | T41: 4.7193485 | U41: 4.5 | W41: émission
A42: GA2A00000051 OTA 2 ANS 4,5% 23-MARS-2020#2 | B42: =MID(A42,1,12) -> GA2A00000051 | C42: Gabon | D42: OTA | E42: 2 ANS | F42: 3282 | G42: 43397 | H42: 43913 | I42: 2980 | J42: 302 | K42: 3282 | N42: 11.111111 | O42: 91.7613 | P42: 21.88 | T42: 4.9170084 | U42: 4.5 | W42: émission
A43: GA2A00000051 | B43: =MID(A43,1,12) -> GA2A00000051 | C43: Gabon | D43: OTA | E43: 2 ANS | F43: 15000 | G43: 43432 | H43: 43913 | I43: 15000 | J43: 0 | K43: 15000 | N43: 22.222222 | O43: 101.7735 | P43: 136.6667 | Q43: 96 | R43: 96 | S43: 100 | T43: 4.4188684 | U43: 4.5 | W43: émission
A44: GA2A00000051 | B44: =MID(A44,1,12) -> GA2A00000051 | C44: Gabon | D44: OTA | E44: 2 ANS | F44: 11000 | G44: 43446 | H44: 43913 | I44: 5000 | J44: 6000 | K44: 11000 | N44: 22.222222 | O44: 99.391 | P44: 93.6 | Q44: 95 | R44: 95 | S44: 97 | T44: 4.5285115 | U44: 4.5 | W44: émission
A45: CM2J00000014 | B45: =MID(A45,1,12) -> CM2J00000014 | C45: Cameroun | D45: OTA | E45: 3 ANS | F45: 14770 | G45: 43516 | H45: 44614 | I45: 12770 | J45: 2000 | K45: 14770 | N45: 28.571429 | O45: 98.515 | P45: 78.2 | Q45: 96.5 | R45: 96.5 | S45: 100 | T45: 3.7563044 | U45: 3.7 | W45: émission
A46: GQ2A00000015 OTA 2 ans 5% 13 février 2021 | B46: =MID(A46,1,12) -> GQ2A00000015 | C46: Guinée Equatoriale | D46: OTA | E46: 2 ANS | F46: 32333.33 | G46: 43509 | H46: 44240 | I46: 32333.33 | J46: 0 | K46: 32333.33 | N46: 0 | T46: 5 | U46: 5 | W46: titrisation
A47: GQ2J00000016 OTA 3 ans 5% 13 février 2022 | B47: =MID(A47,1,12) -> GQ2J00000016 | C47: Guinée Equatoriale | D47: OTA | E47: 3 ANS | F47: 32333.33 | G47: 43509 | H47: 44605 | I47: 32333.33 | J47: 0 | K47: 32333.33 | N47: 0 | T47: 5 | U47: 5 | W47: titrisation
A48: GQ2K00000013 OTA 4 ans 5% 13 février 2023 | B48: =MID(A48,1,12) -> GQ2K00000013 | C48: Guinée Equatoriale | D48: OTA | E48: 4 ANS | F48: 32333.33 | G48: 43509 | H48: 44970 | I48: 32333.33 | J48: 0 | K48: 32333.33 | N48: 0 | T48: 5 | U48: 5 | W48: titrisation
A49: GQ2B00000014 OTA 5 ans 5% 13 février 2024 | B49: =MID(A49,1,12) -> GQ2B00000014 | C49: Guinée Equatoriale | D49: OTA | E49: 5 ANS | F49: 32333.33 | G49: 43509 | H49: 45335 | I49: 32333.33 | J49: 0 | K49: 32333.33 | N49: 0 | T49: 5 | U49: 5 | W49: titrisation
A50: GQ2L00000012 OTA 6 ans 5% 13 février 2025 | B50: =MID(A50,1,12) -> GQ2L00000012 | C50: Guinée Equatoriale | D50: OTA | E50: 6 ANS | F50: 32333.33 | G50: 43509 | H50: 45701 | I50: 32333.33 | J50: 0 | K50: 32333.33 | N50: 0 | T50: 5 | U50: 5 | W50: titrisation
A51: GQ2C00000013 OTA 7 ans 5% 13 février 2026 | B51: =MID(A51,1,12) -> GQ2C00000013 | C51: Guinée Equatoriale | D51: OTA | E51: 7 ANS | F51: 32333.33 | G51: 43509 | H51: 46066 | I51: 32333.33 | J51: 0 | K51: 32333.33 | N51: 0 | T51: 5 | U51: 5 | W51: titrisation
A52: GQ2M00000011 OTA 8 ans 5% 13 février 2027 | B52: =MID(A52,1,12) -> GQ2M00000011 | C52: Guinée Equatoriale | D52: OTA | E52: 8 ANS | F52: 32333.33 | G52: 43509 | H52: 46431 | I52: 32333.33 | J52: 0 | K52: 32333.33 | N52: 0 | T52: 5 | U52: 5 | W52: titrisation
A53: GQ2N00000010 OTA 9 ans 5% 13 février 2028 | B53: =MID(A53,1,12) -> GQ2N00000010 | C53: Guinée Equatoriale | D53: OTA | E53: 9 ANS | F53: 32333.33 | G53: 43509 | H53: 46796 | I53: 32333.33 | J53: 0 | K53: 32333.33 | N53: 0 | T53: 5 | U53: 5 | W53: titrisation
A54: GQ2D00000012 OTA 10 ans 5% 13 février 2029 | B54: =MID(A54,1,12) -> GQ2D00000012 | C54: Guinée Equatoriale | D54: OTA | E54: 10 ANS | F54: 32333.33 | G54: 43509 | H54: 47162 | I54: 32333.33 | J54: 0 | K54: 32333.33 | N54: 0 | T54: 5 | U54: 5 | W54: titrisation
A55: GA2J00000085 | B55: =MID(A55,1,12) -> GA2J00000085 | C55: Gabon | D55: OTA | E55: 3 ANS | F55: 15000 | G55: 43565 | H55: 44649 | I55: 15000 | J55: 0 | K55: 15000 | N55: 5.5555556 | O55: 99.2199 | P55: 85.7143 | Q55: 99 | R55: 99 | S55: 99 | T55: 5.7953541 | U55: 5.75 | W55: émission
A56: CM2J00000022 | B56: =MID(A56,1,12) -> CM2J00000022 | C56: Cameroun | D56: OTA | E56: 3 ANS | F56: 72540 | G56: 43607 | H56: 44705 | I56: 64540 | J56: 8000 | K56: 72540 | N56: 38.095238 | O56: 99.6726 | P56: 77.14 | Q56: 98 | R56: 98 | S56: 100 | T56: 4.0132445 | U56: 4 | W56: émission
A57: CM2K00000011 | B57: =MID(A57,1,12) -> CM2K00000011 | C57: Cameroun | D57: OTA | E57: 4 ANS | F57: 48482 | G57: 43614 | H57: 45077 | I57: 48482 | J57: 0 | K57: 48482 | N57: 28.571429 | O57: 98.2785 | P57: 48.654 | Q57: 96 | R57: 96 | S57: 100 | T57: 4.8332768 | U57: 4.75 | W57: émission
A58: GA2J00000069 | B58: =MID(A58,1,12) -> GA2J00000069 | C58: Gabon | D58: OTA | E58: 3 ANS | F58: 8500 | G58: 43593 | H58: 44382 | I58: 1500 | J58: 7000 | K58: 8500 | N58: 22.222222 | O58: 101.8226 | P58: 85 | Q58: 94 | R58: 94 | S58: 100 | T58: 5.6447349 | U58: 5.75 | W58: émission
A59: CG2A00000015 | B59: =MID(A59,1,12) -> CG2A00000015 | C59: Congo | D59: OTA | E59: 2 ANS | F59: 22500 | G59: 43635 | H59: 44368 | I59: 0 | J59: 22500 | K59: 22500 | N59: 8.6956522 | O59: 88.5556 | P59: 120 | Q59: 87 | R59: 87 | S59: 90 | T59: 7.3538376 | U59: 6.5 | W59: émission
A60: CM2B00000020 | B60: =MID(A60,1,12) -> CM2B00000020 | C60: Cameroun | D60: OTA | E60: 5 ANS | F60: 100000 | G60: 43628 | H60: 45457 | I60: 53585.1 | J60: 0 | K60: 53585.1 | N60: 23.809524 | O60: 98.175 | P60: 53.5851 | Q60: 96 | R60: 96 | S60: 100 | T60: 5.7041077 | U60: 5.6 | W60: émission
A61: GA2J00000085 | B61: =MID(A61,1,12) -> GA2J00000085 | C61: Gabon | D61: OTA | E61: 3 ANS | F61: 18050 | G61: 43649.583 | H61: 44649 | I61: 2000 | J61: 16050 | K61: 18050 | N61: 16.666667 | O61: 99.86 | P61: 90.25 | Q61: 94 | R61: 94 | S61: 100 | T61: 5.7580875 | U61: 5.75 | W61: émission
A62: CM2B00000020 | B62: =MID(A62,1,12) -> CM2B00000020 | C62: Cameroun | D62: OTA | E62: 5 ANS | F62: 18418 | G62: 43677.646 | H62: 45457 | I62: 18418 | J62: 0 | K62: 18418 | N62: 28.571429 | O62: 99 | P62: 24.418 | Q62: 96.5 | R62: 96.5 | S62: 100 | T62: 5.65657 | U62: 5.6 | W62: émission
A63: CM2J00000022 | B63: =MID(A63,1,12) -> CM2J00000022 | C63: Cameroun | D63: OTA | E63: 3 ANS | F63: 10500 | G63: 43698.583 | H63: 44705 | I63: 10500 | J63: 0 | K63: 10500 | N63: 14.285714 | O63: 98.9945 | P63: 28 | Q63: 98 | R63: 98 | S63: 98 | T63: 4.0409515 | U63: 4 | W63: émission
A64: CG2A00000023 | B64: =MID(A64,1,12) -> CG2A00000023 | C64: Congo | D64: OTA | E64: 2 ANS | F64: 24000 | G64: 43712 | H64: 44445 | I64: 20000 | J64: 4000 | K64: 24000 | N64: 21.73913 | O64: 90.4167 | P64: 136 | Q64: 90 | R64: 90 | S64: 90 | T64: 7.2004576 | U64: 6.5 | W64: émission
A65: CG2A00000031 | B65: =MID(A65,1,12) -> CG2A00000031 | C65: Congo | D65: OTA | E65: 2 ANS | F65: 15000 | G65: 43719 | H65: 44452 | I65: 15000 | J65: 0 | K65: 15000 | N65: 8.6956522 | O65: 89.33 | P65: 100 | Q65: 89 | R65: 89 | S65: 90 | T65: 7.2892493 | U65: 6.5 | W65: émission
A66: GA2B00000026 | B66: =MID(A66,1,12) -> GA2B00000026 | C66: Gabon | D66: OTA | E66: 5 ANS | F66: 20500 | G66: 43712 | H66: 45141 | I66: 18000 | J66: 2500 | K66: 20500 | N66: 16.666667 | O66: 99.6747 | P66: 91.1111 | Q66: 92 | R66: 92 | S66: 92 | T66: 7.0228508 | U66: 7 | W66: émission
... A70: GA2J00000093 | B70: =MID(A70,1,12) -> GA2J00000093 | C70: Gabon | D70: OTA | E70: 3 ANS | F70: 11231.12 | G70: 43761 | H70: 44859 | I70: 4000 | J70: 7231.12 | K70: 11231.12 | N70: 22.222222 | O70: 91.8698 | P70: 89.849 | Q70: 90 | R70: 95 | S70: 90 | T70: 8.11 | U70: 5 | W70: émission
A71: CG2A00000049/MN | B71: =MID(A71,1,12) -> CG2A00000049 | C71: Congo | D71: OTA | E71: 2 ANS | F71: 40000 | G71: 43789.667 | H71: 44522 | I71: 20000 | J71: 12000 | K71: 32000 | N71: 17.391304 | O71: 91.6938 | P71: 80 | Q71: 90 | R71: 96 | S71: 90 | T71: 10.99 | W71: émission
A72: CG2J00000016/MN | B72: =MID(A72,1,12) -> CG2J00000016 | C72: Congo | D72: OTA | E72: 3 ANS | F72: 40000 | G72: 43782.667 | H72: 44880 | I72: 30000 | J72: 0 | K72: 30000 | N72: 13.043478 | O72: 94.675 | P72: 80 | Q72: 94 | R72: 98.5 | S72: 94 | T72: 8.55 | W72: émission
A73: GA2A00000076/MN1 | B73: =MID(A73,1,12) -> GA2A00000076 | C73: Gabon | D73: OTA | E73: 2 ANS | F73: 20000 | G73: 43803 | H73: 44431 | I73: 700 | J73: 19300 | K73: 20000 | N73: 27.777778 | O73: 89 | P73: 131 | Q73: 89 | R73: 97 | S73: 89 | T73: 8.7 | W73: émission
A74: GA2J00000093/MN2 | B74: =MID(A74,1,12) -> GA2J00000093 | C74: Gabon | D74: OTA | E74: 3 ANS | F74: 20000 | G74: 43803.5 | H74: 44859 | I74: 0 | J74: 20000 | K74: 20000 | N74: 11.111111 | O74: 88.2588 | P74: 100 | Q74: 87.3 | R74: 95 | S74: 87.3 | T74: 9.6 | W74: émission
A75: GA2J00000093/MN3 | B75: =MID(A75,1,12) -> GA2J00000093 | C75: Gabon | D75: OTA | E75: 3 ANS | F75: 7500 | G75: 43824.5 | H75: 44859 | I75: 0 | J75: 5000 | K75: 5000 | N75: 11.111111 | O75: 92.3607 | P75: 93.3333 | Q75: 90 | R75: 93 | S75: 90 | T75: 7.91 | W75: émission
A76: GA2A00000076/MN2 | B76: =MID(A76,1,12) -> GA2A00000076 | C76: Gabon | D76: OTA | E76: 2 ANS | F76: 15000 | G76: 43824.5 | H76: 44431 | I76: 0 | J76: 13700 | K76: 13700 | N76: 16.666667 | O76: 94.0659 | P76: 91.3333 | Q76: 89 | R76: 95 | S76: 89 | T76: 8.02 | W76: émission
A77: CG2A00000056/MN | B77: =MID(A77,1,12) -> CG2A00000056 | C77: Congo | D77: OTA | E77: 2 ANS | F77: 35000 | G77: 43810.667 | H77: 44543 | I77: 20000 | J77: 10000 | K77: 30000 | N77: 8.6956522 | O77: 90 | P77: 85.7143 | Q77: 90 | R77: 90 | S77: 90 | T77: 12.02 | W77: émission
A78: GA2A00000084/MN | B78: =MID(A78,1,12) -> GA2A00000084 | C78: Gabon | D78: OTA | E78: 2 ANS | F78: 12500 | G78: 43859.5 | H78: 44592 | I78: 0 | J78: 12500 | K78: 12500 | N78: 16.666667 | O78: 91.0422 | P78: 141.76 | Q78: 90.1 | R78: 95 | S78: 90 | T78: 9.76 | U78: 4.75 | W78: émission
A79: CG2A00000072/MN | B79: =MID(A79,1,12) -> CG2A00000072 | C79: Congo | D79: OTA | E79: 2 ANS | F79: 30000 | G79: 43860.708 | H79: 44592 | I79: 30000 | J79: 0 | K79: 30000 | N79: 8.6956522 | O79: 90.09333 | P79: 110 | Q79: 90 | R79: 91 | S79: 90 | T79: 11.18 | U79: 6 | W79: émission
A80: CG2A00000072 | B80: =MID(A80,1,12) -> CG2A00000072 | C80: Congo | D80: OTA | E80: 2 ANS | F80: 11000 | G80: 43866 | H80: 44592 | I80: 8333.33 | J80: 1666.67 | K80: 10000 | N80: 13.043478 | O80: 90.6154 | P80: 110 | Q80: 90 | R80: 91 | S80: 90 | T80: 11.38 | U80: 6 | W80: émission
A81: GA2J00000101 | B81: =MID(A81,1,12) -> GA2J00000101 | C81: Gabon | D81: OTA | E81: 3 ANS | F81: 15000 | G81: 43880 | H81: 44978 | I81: 0 | J81: 11300 | K81: 11300 | N81: 22.222222 | O81: 92.0243 | P81: 123.667 | Q81: 91.5 | R81: 95 | S81: 91 | T81: 8.05 | U81: 5 | W81: émission
A82: CG2A00000080/MN | B82: =MID(A82,1,12) -> CG2A00000080 | C82: Congo | D82: OTA | E82: 2 ANS | F82: 35000 | G82: 43894.708 | H82: 44626 | I82: 29533.46 | J82: 5466.54 | K82: 35000 | N82: 30.434783 | O82: 91.245 | P82: 120.2 | Q82: 90 | R82: 96 | S82: 90 | T82: 11 | U82: 6 | W82: émission
A83: GA2K00000017/ | B83: =MID(A83,1,12) -> GA2K00000017 | C83: Gabon | D83: OTA | E83: 4 ANS | F83: 17500 | G83: 44272 | H83: 45371 | I83: 700 | J83: 16800 | K83: 17500 | N83: 27.777778 | O83: 87.4086 | P83: 109.1429 | Q83: 86 | R83: 93 | S83: 86 | T83: 10.43 | U83: 6.5 | W83: émission
A84: GA2J00000101/MN1 | B84: =MID(A84,1,12) -> GA2J00000101 | C84: Gabon | D84: OTA | E84: 3 ANS | F84: 20000 | G84: 43908.625 | H84: 44978 | I84: 1500 | J84: 12500 | K84: 14000 | N84: 11.111111 | O84: 88.3289 | P84: 71 | Q84: 87 | R84: 91.5 | S84: 87 | T84: 9.57 | U84: 5 | W84: émission
A85: CM2B00000038/MN1 | B85: =MID(A85,1,12) -> CM2B00000038 | C85: Cameroun | D85: OTA | E85: 5 ANS | F85: 100000 | G85: 43929 | H85: 45757 | I85: 71637.8 | J85: 0 | K85: 71637.8 | N85: 33.333333 | O85: 97.6512 | P85: 75.6378 | Q85: 96 | R85: 100 | S85: 96 | T85: 5.7 | U85: 5.7 | W85: émission
A86: CG2A00000098/MN | B86: =MID(A86,1,12) -> CG2A00000098 | C86: Congo | D86: OTA | E86: 2 ANS | F86: 15000 | G86: 43929 | H86: 44661 | I86: 10711.57 | J86: 4288.43 | K86: 15000 | N86: 17.391304 | O86: 92.3333 | P86: 115.3667 | Q86: 92 | R86: 92 | S86: 92 | T86: 10.34 | U86: 6 | W86: émission
A87: CM2J00000030/MN | B87: =MID(A87,1,12) -> CM2J00000030 | C87: Cameroun | D87: OTA | E87: 3 ANS | F87: 70000 | G87: 43936 | H87: 45033 | I87: 35000 | J87: 0 | K87: 35000 | N87: 28.571429 | O87: 96.4243 | P87: 52.9236 | Q87: 95 | R87: 100 | S87: 95 | T87: 5.31 | U87: 4 | W87: émission
A88: GA2A00000084/MN1 | B88: =MID(A88,1,12) -> GA2A00000084 | C88: Gabon | D88: OTA | E88: 2 ANS | F88: 20000 | G88: 43936 | H88: 44592 | I88: 2500 | J88: 10930 | K88: 13430 | N88: 22.222222 | O88: 92.9137 | P88: 67.15 | Q88: 90 | R88: 92 | S88: 90 | T88: 8.69 | U88: 4.75 | W88: émission
A89: GA2K00000017/MN1 | B89: =MID(A89,1,12) -> GA2K00000017 | C89: Gabon | D89: OTA | E89: 4 ANS | F89: 15000 | G89: 43936 | H89: 45371 | I89: 571 | J89: 0 | K89: 571 | N89: 5.5555556 | O89: 99.4802 | P89: 3.8067 | Q89: 98.5 | R89: 99 | S89: 98.5 | T89: 6.65 | U89: 6.5 | W89: émission
... A127: CG2B00000014/MN | B127: =MID(A127,1,12) -> CG2B00000014 | C127: Congo | D127: OTA | E127: 5 ANS | F127: 32000 | G127: 44139 | H127: 45966 | I127: 30714.36 | J127: 0 | K127: 30714.36 | N127: 4.3478261 | O127: 96.2278 | P127: 95.9824 | Q127: 96.21 | R127: 96.21 | S127: 96.21 | T127: 7.72 | U127: 6.5 | W127: émission
A128: CG2A00000155/MN | B128: =MID(A128,1,12) -> CG2A00000155 | C128: Congo | D128: OTA | E128: 2 ANS | F128: 32000 | G128: 44139 | H128: 44871 | I128: 30714.44 | K128: 30714.44 | N128: 4.3478261 | O128: 96.21 | P128: 95.9826 | Q128: 96.21 | R128: 96.21 | S128: 96.21 | T128: 8.09 | U128: 6 | W128: émission
A129: CG2J00000065/MN | B129: =MID(A129,1,12) -> CG2J00000065 | C129: Congo | D129: OTA | E129: 3 ANS | F129: 32000 | G129: 44139 | H129: 45236 | I129: 30714.42 | J129: 0 | K129: 30714.42 | N129: 4.3478261 | O129: 96.21 | P129: 95.9826 | Q129: 96.21 | R129: 96.21 | S129: 96.21 | T129: 7.74 | U129: 6.3 | W129: émission
A130: CM2C00000045/MN | B130: =MID(A130,1,12) -> CM2C00000045 | C130: Cameroun | D130: OTA | E130: 7 ANS | F130: 0 | G130: 44139 | H130: 46697 | I130: 0 | J130: 0 | K130: 0 | N130: 19.047619 | O130: 0 | P130: 0 | Q130: 0 | R130: 0 | S130: 0 | T130: 0 | U130: 0 | W130: émission
A131: GA2B00000042/MN4 | B131: =MID(A131,1,12) -> GA2B00000042 | C131: Gabon | D131: OTA | E131: 5 ANS | F131: 20000 | G131: 44146 | H131: 45925 | I131: 14462 | J131: 5538 | K131: 20000 | N131: 27.777778 | O131: 93.9163 | P131: 155.6433 | Q131: 88 | R131: 95 | S131: 88 | T131: 8 | U131: 6.5 | W131: émission
A132: GA2J00000135/MN3 | B132: =MID(A132,1,12) -> GA2J00000135 | C132: Gabon | D132: OTA | E132: 3 ANS | F132: 25000 | G132: 44146 | H132: 45215 | I132: 14011 | J132: 10989 | K132: 25000 | N132: 27.777778 | O132: 94.7393 | P132: 100 | Q132: 92 | R132: 100 | S132: 92 | T132: 7.23 | U132: 5.25 | W132: émission
A133: CG2A00000163/MN | B133: =MID(A133,1,12) -> CG2A00000163 | C133: Congo | D133: OTA | E133: 2 ANS | F133: 15000 | G133: 44146 | H133: 44878 | I133: 14967.7 | J133: 32.3 | K133: 15000 | N133: 21.73913 | O133: 90.1983 | P133: 101.2513 | Q133: 90 | R133: 96 | S133: 90 | T133: 11.63 | U133: 6 | W133: émission
A134: CM2A00000062/MN | B134: =MID(A134,1,12) -> CM2A00000062 | C134: Cameroun | D134: OTA | E134: 2 ANS | F134: 35000 | G134: 44153 | H134: 44885 | I134: 20000 | J134: 8000 | K134: 28000 | N134: 28.571429 | O134: 99.7929 | P134: 86 | Q134: 99 | R134: 100 | S134: 99 | T134: 3.51 | U134: 3.4 | W134: émission
A135: GA2B00000059/MN | B135: =MID(A135,1,12) -> GA2B00000059 | C135: Gabon | D135: OTA | E135: 5 ANS | F135: 30000 | G135: 44160 | H135: 45988 | I135: 15425 | J135: 14575 | K135: 30000 | N135: 44.444444 | O135: 87.8179 | P135: 100 | Q135: 87 | R135: 98 | S135: 87 | T135: 9.63 | U135: 6.5 | W135: émission
A136: GA2A00000118/MN | B136: =MID(A136,1,12) -> GA2A00000118 | C136: Gabon | D136: OTA | E136: 2 ANS | F136: 17500 | G136: 44160 | H136: 44766 | I136: 13700 | J136: 3800 | K136: 17500 | N136: 27.777778 | O136: 94.1041 | P136: 100.3429 | Q136: 90 | R136: 95 | S136: 90 | T136: 8 | U136: 4.75 | W136: émission
A137: CG2J00000073/MN | B137: =MID(A137,1,12) -> CG2J00000073 | C137: Congo | D137: OTA | E137: 3 ANS | F137: 30000 | G137: 44167 | H137: 45264 | I137: 9688.18 | J137: 1585 | K137: 11273.18 | N137: 21.73913 | O137: 90.356 | P137: 37.5773 | Q137: 90 | R137: 95 | S137: 90 | T137: 9.79 | U137: 6 | W137: émission
A138: CF2A00000017 | B138: =MID(A138,1,12) -> CF2A00000017 | C138: République centrafricaine | D138: OTA | E138: 2 ANS | F138: 3657.15 | G138: 44167 | H138: 44899 | I138: 0 | J138: 0 | K138: 3657.15 | N138: 0 | O138: 0 | P138: 0 | Q138: 0 | R138: 0 | S138: 0 | T138: 2.95 | U138: 2.95 | W138: titrisation
A139: CF2B00000016 | B139: =MID(A139,1,12) -> CF2B00000016 | C139: République centrafricaine | D139: OTA | E139: 5 ANS | F139: 3657.16 | G139: 44167 | H139: 45995 | I139: 0 | J139: 0 | K139: 3657.16 | N139: 0 | O139: 0 | P139: 0 | Q139: 0 | R139: 0 | S139: 0 | T139: 2.95 | U139: 2.95 | W139: titrisation
A140: CF2J00000018 | B140: =MID(A140,1,12) -> CF2J00000018 | C140: République centrafricaine | D140: OTA | E140: 3 ANS | F140: 3657.16 | G140: 44167 | H140: 45264 | I140: 0 | J140: 0 | K140: 3657.16 | N140: 0 | O140: 0 | P140: 0 | Q140: 0 | R140: 0 | S140: 0 | T140: 2.95 | U140: 2.95 | W140: titrisation
...

Sheet REMBOURSEMENTS
A1: TABLEAU DE SUIVI DES REMBOURSEMENTS — CTDAM-CEMAC
A3: Code Long | B3: Code Court | C3: Pays | D3: Instrument | E3: Maturité | F3: Montant Émis (M XAF) | G3: Jour Souscription | H3: Date Remboursement | I3: Nature (Coupon/Principal) | J3: Montant Dû (M XAF) | K3: Montant Payé (M XAF) | L3: Date Paiement Effectif
A4: XACMRBTA2026013 | B4: CMRBTA13W | C4: CMR | D4: BTA | E4: 13 semaines | F4: 10000 | G4: 2026-01-15 | H4: 2026-04-16 | I4: Principal | J4: 10000 | K4: 10000 | L4: 2026-04-16
A5: XACMROTA20265 | B5: CMROTA5A | C5: CMR | D5: OTA | E5: 5 ans | F5: 50000 | G5: 2026-02-10 | H5: 2031-02-10 | I5: Coupon | J5: 3500 | K5: 3500 | L5: 2027-02-10
A6: XACMROTA20265 | B6: CMROTA5A | C6: CMR | D6: OTA | E6: 5 ans | F6: 50000 | G6: 2026-02-10 | H6: 2031-02-10 | I6: Principal | J6: 50000 | L6: 2031-02-10

Sheet SVT
A1: RÉPERTOIRE DES SVT — Spécialistes en Valeurs du Trésor
A3: Raison Sociale | B3: Code SVT | C3: Pays | D3: Région/Ville | E3: Date Convention | F3: N° Agrément | G3: Statut | H3: Capital Social (M XAF) | I3: Email Front Office | J3: Email Middle Office | K3: Email Back Office | L3: Téléphone | M3: Site Web | N3: Représentant légal | O3: Nb Adjudications | P3: Encours Détenu (M XAF)
A4: Société Générale Cameroun | B4: SGC-CMR-001 | C4: CMR | D4: Yaoundé | E4: 2023-01-15 | F4: CMF-SVT-001 | G4: Actif | H4: 50000 | I4: s.mbarga@sgcam.cm | J4: operations@sgcam.cm | K4: backoffice@sgcam.cm | L4: +237 222 23 40 | M4: www.sgcam.cm | N4: Jean MBARGA
A5: Afriland First Bank | B5: AFB-CMR-001 | C5: CMR | D5: Yaoundé | E5: 2022-06-10 | F5: CMF-SVT-002 | G5: Actif | H5: 30000 | I5: trading@afriland.cm | J5: midoff@afriland.cm | K5: back@afriland.cm | L5: +237 233 50 31 | M5: www.afriland.com | N5: Paul NDJODO
A6: BGFI Bank Gabon | B6: BGFI-GAB-001 | C6: GAB | D6: Libreville | E6: 2022-09-05 | F6: COB-SVT-001 | G6: Actif | H6: 45000 | I6: tresor@bgfi.ga | J6: middle@bgfi.ga | K6: back@bgfi.ga | L6: +241 01 76 22 00 | M6: www.bgfi.com | N6: Marie NGUEMA

Sheet SGP
A1: RÉPERTOIRE DES SGP — Sociétés de Gestion et de Portefeuille
A3: Dénomination | B3: Code SGP | C3: Pays | D3: Ville | E3: N° Agrément Régulateur | F3: Date Agrément | G3: Statut | H3: AUM (M XAF) | I3: Contact Principal | J3: Email | K3: Téléphone | L3: Site Web
A4: CGF Bourse | B4: CGF-CMR-001 | C4: CMR | D4: Douala | E4: CMF-SGP-001 | F4: 2021-03-10 | G4: Actif | H4: 25000 | I4: M. TCHAMBA | J4: info@cgfbourse.cm | K4: +237 233 42 20 | L4: www.cgfbourse.cm
A5: EDC Investments | B5: EDC-CMR-002 | C5: CMR | D5: Yaoundé | E5: CMF-SGP-002 | F5: 2022-07-15 | G5: Actif | H5: 18000 | I5: M. FOUDA | J5: invest@edcgroup.cm | K5: +237 222 00 11 | L5: www.edcgroup.cm

Sheet SDB
A1: RÉPERTOIRE DES SDB — Sociétés de Bourse
A3: Dénomination | B3: Code SDB | C3: Pays | D3: Ville | E3: N° Agrément | F3: Date Agrément | G3: Statut | H3: Email | I3: Téléphone | J3: Site Web
A4: Douala Stock Exchange | B4: DSX-CMR-001 | C4: CMR | D4: Douala | E4: DSX-001 | F4: 2001-04-23 | G4: Actif | H4: info@douala-stock-exchange.com | I4: +237 233 42 77 | J4: www.douala-stock-exchange.com
A5: BVMAC | B5: BVMAC-GAB-001 | C5: GAB | D5: Libreville | E5: BVMAC-001 | F5: 2003-06-15 | G5: Actif | H5: contact@bvmac.org | I5: +241 01 76 40 50 | J5: www.bvmac.org

Sheet INVESTISSEURS_INST
A1: RÉPERTOIRE DES INVESTISSEURS INSTITUTIONNELS
A3: Dénomination | B3: Type Acteur | C3: Pays | D3: Ville | E3: Point Focal | F3: Email | G3: Téléphone | H3: Statut | I3: AUM Approx. (M XAF) | J3: SVT Référent | K3: Date Validation | L3: N° Dossier
A4: CNPS | B4: Institutionnel | C4: Cameroun | D4: Yaoundé | E4: Yaoundé-Hipodromme | F4: cnpscmr@gmail.com | G4: 698563214 | H4: Actif

Sheet UTILISATEURS
A1: GESTION DES UTILISATEURS DE LA PLATEFORME
A3: Username | B3: Email | C3: Nom Complet | D3: Type Acteur | E3: Pays | F3: N° Agrément | G3: Statut Compte | H3: Rôle Plateforme | I3: Date Inscription | J3: Date Validation | K3: Validé par | L3: Actif
A4: admin_beac | B4: admin@beac.int | C4: Admin BEAC | G4: Validé | H4: Administrateur | L4: Oui

Sheet PAYS_MACRO
A1: DONNÉES MACROÉCONOMIQUES PAR PAYS — Annuelles
A3: SOURCE : Banque Mondiale, BEAC, FMI — Mettre à jour annuellement
A4: Pays | B4: Code Pays | C4: Année | D4: PIB (Mds XAF) | E4: Croissance PIB (%) | F4: Inflation (%) | G4: Solde Budgétaire (% PIB) | H4: Recettes Fiscales (Mds XAF) | I4: Dépenses Totales (Mds XAF) | J4: Déficit Extérieur (% PIB) | K4: Dette Publique Totale (Mds XAF) | L4: Dette / PIB (%) | M4: Service de la Dette (Mds XAF) | N4: Service Dette / Recettes Fiscales (%) | O4: Projection Recettes N+1 (Mds XAF) | P4: Projection Dépenses N+1 (Mds XAF)
A5: Cameroun | B5: CMR | C5: 2024 | D5: 28500 | E5: 3.8 | F5: 2.4 | G5: -1.8 | H5: 4200 | I5: 5500 | J5: -3.2 | K5: 9800 | L5: 34.4 | M5: 820 | N5: 19.5% | O5: 4500 | P5: 5800
A6: Gabon | B6: GAB | C6: 2024 | D6: 13200 | E6: 2.9 | F6: 3.1 | G6: -2.1 | H6: 2100 | I6: 3200 | J6: -4.1 | K6: 5100 | L6: 38.6 | M6: 420 | N6: 20.0% | O6: 2200 | P6: 3400
A7: Congo | B7: COG | C7: 2024 | D7: 6800 | E7: 4.2 | F7: 2.8 | G7: -0.9 | H7: 980 | I7: 1450 | J7: -2.8 | K7: 3200 | L7: 47.1 | M7: 310 | N7: 31.6% | O7: 1050 | P7: 1500
A8: RCA | B8: RCA | C8: 2024 | D8: 1250 | E8: 1.9 | F8: 5.6 | G8: -4.2 | H8: 180 | I8: 380 | J8: -8.1 | K8: 850 | L8: 68 | M8: 75 | N8: 41.7% | O8: 190 | P8: 390
A9: Guinée Équatoriale | B9: GNQ | C9: 2024 | D9: 5800 | E9: -1.2 | F9: 2.9 | G9: -3.5 | H9: 890 | I9: 1480 | J9: -5.2 | K9: 2200 | L9: 37.9 | M9: 200 | N9: 22.5% | O9: 920 | P9: 1520
A10: Tchad | B10: TCD | C10: 2024 | D10: 4900 | E10: 3.1 | F10: 3.8 | G10: -2.8 | H10: 650 | I10: 1100 | J10: -6.1 | K10: 2800 | L10: 57.1 | M10: 180 | N10: 27.7% | O10: 680 | P10: 1150
A11: → Somme CEMAC | D11: =SUM(D5:D10) -> 60450 | H11: =SUM(H5:H10) -> 9000 | K11: =SUM(K5:K10) -> 23950

Sheet ENCOURS_MENSUEL
A1: ENCOURS MENSUELS PAR PAYS ET INSTRUMENT (M XAF)
A3: Pays | B3: Code Pays | C3: Mois (YYYY-MM) | D3: Instrument (BTA/OTA) | E3: Maturité | F3: Encours (M XAF) | G3: Encours Cumulé Pays (M XAF) | H3: Variation M/M (%) | I3: Variation A/A (%) | J3: Nb Titres Actifs | K3: Source/Remarque
A4: Cameroun | B4: CMR | C4: 2026-03 | D4: BTA | E4: 13 semaines | F4: 320000 | G4: =SUMIF($B$4:$B$100,B4,$F$4:$F$100) -> 1250000 | J4: 12 | K4: Importé BEAC
A5: Cameroun | B5: CMR | C5: 2026-03 | D5: BTA | E5: 26 semaines | F5: 180000 | J5: 8 | K5: Importé BEAC
A6: Cameroun | B6: CMR | C6: 2026-03 | D6: OTA | E6: 5 ans | F6: 750000 | J6: 15 | K6: Importé BEAC
A7: Gabon | B7: GAB | C7: 2026-03 | D7: BTA | E7: 13 semaines | F7: 180000 | J7: 9 | K7: Importé BEAC
A8: Gabon | B8: GAB | C8: 2026-03 | D8: OTA | E8: 7 ans | F8: 350000 | J8: 7 | K8: Importé BEAC

Sheet CALENDRIER_EMISSIONS
A1: CALENDRIER PRÉVISIONNEL DES ÉMISSIONS
A3: Pays | B3: Code Pays | C3: Instrument | D3: Maturité | E3: Date Adjudication | F3: Heure Limite | G3: Montant Indicatif (M XAF) | H3: Statut | I3: Référence BEAC | J3: Remarque | K3: Résultat Publié
A4: Cameroun | B4: CMR | C4: BTA | D4: 13 semaines | E4: 2026-05-28 | F4: 11h00 | G4: 10000 | H4: Confirmé | I4: BEAC/2026/015
A5: Gabon | B5: GAB | C5: OTA | D5: 5 ans | E5: 2026-06-03 | F5: 11h00 | G5: 30000 | H5: Prévisionnel | I5: BEAC/2026/016
A6: Congo | B6: COG | C6: BTA | D6: 26 semaines | E6: 2026-06-10 | F6: 11h00 | G6: 5000 | H6: Prévisionnel | I6: BEAC/2026/017

Sheet COURBE_TAUX
A1: COURBE DES TAUX — CEMAC (Rendement à l'échéance)
A2: Mettre à jour après chaque adjudication — valeurs en %
A3: Date | B3: Maturité Label | C3: Maturité (années) | D3: Taux CEMAC moyen (%) | E3: Taux Cameroun (%) | F3: Taux Gabon (%) | G3: Taux Congo (%) | H3: Taux RCA (%) | I3: Taux GNQ (%) | J3: Taux Tchad (%) | K3: Variation vs J-1 (bp) | L3: Source
A4: 2026-03-31 | B4: 13 semaines | C4: 0.25 | D4: 3.35 | E4: 3.35 | F4: 3.4 | G4: 3.45 | H4: 4.1 | I4: 3.5 | J4: 3.9 | K4: +5 | L4: -
A5: 2026-03-31 | B5: 26 semaines | C5: 0.5 | D5: 4.15 | E5: 4.1 | F5: 4.2 | G5: 4.3 | J5: 4.5 | K5: -2 | L5: -
A6: 2026-03-31 | B6: 52 semaines | C6: 1 | D6: 5 | E6: 4.95 | F6: 5.1 | G6: 5.2 | K6: +8 | L6: -
A7: 2026-03-31 | B7: 2 ans | C7: 2 | D7: 5.8 | E7: 5.75 | F7: 5.9 | K7: +3 | L7: -
A8: 2026-03-31 | B8: 3 ans | C8: 3 | D8: 6.3 | E8: 6.25 | F8: 6.4 | K8: +2 | L8: -
A9: 2026-03-31 | B9: 5 ans | C9: 5 | D9: 7.1 | E9: 7.05 | F9: 7.2 | K9: +5 | L9: -
A10: 2026-03-31 | B10: 7 ans | C10: 7 | D10: 7.6 | E10: 7.55 | F10: 7.7 | K10: +4 | L10: -
A11: 2026-03-31 | B11: 10 ans | C11: 10 | D11: 8.2 | E11: 8.15 | F11: 8.3 | K11: +6 | L11: -
A12: 2026-03-31 | B12: 15 ans | C12: 15 | D12: 8.9 | E12: 8.85 | F12: 9 | K12: +5 | L12: -

Sheet CALCULS_MARCHE
A1: CALCULS DE MARCHÉ — Prix, Duration, Convexité, Spread
A2: Données calculées / importées pour les outils de simulation
A3: Code ISIN | B3: Pays | C3: Instrument | D3: Maturité | E3: Date Valeur | F3: Taux Facial (%) | G3: Prix Pied de Coupon (%) | H3: Prix Pied de Coupon + Coupon Couru (%) | I3: Rendement à l'Échéance (%) | J3: Duration (années) | K3: Duration Modifiée | L3: Convexité | M3: Spread vs BTA 13s (bp) | N3: Liquidité (1=Faible..5=Elevée)
A4: XACMROTA20265 | B4: CMR | C4: OTA | D4: 5 ans | E4: 2026-03-31 | F4: 7.00% | G4: 98.50 | H4: 99.25 | I4: 7.32% | J4: 4.18 | K4: 3.89 | L4: 21.4 | M4: 375 bp | N4: 4
A5: XAGABOTA20267 | B5: GAB | C5: OTA | D5: 7 ans | E5: 2026-03-31 | F5: 7.50% | G5: 97.80 | H5: 98.60 | I5: 7.85% | J5: 5.62 | K5: 5.20 | L5: 38.2 | M5: 435 bp | N5: 3

Sheet DETENTEURS
A1: RÉPARTITION DES ENCOURS PAR CATÉGORIE DE DÉTENTEURS
A3: Date (YYYY-MM) | B3: Pays | C3: Catégorie Détenteur | D3: Encours (M XAF) | E3: Part (%) | F3: Variation M/M (M XAF) | G3: Source
A4: 2026-03 | B4: CEMAC | C4: SVT | D4: 2041000 | E4: 42.3% | G4: BEAC
A5: 2026-03 | B5: CEMAC | C5: Autres banques | D5: 902700 | E5: 18.7% | G5: BEAC
A6: 2026-03 | B6: CEMAC | C6: Institutionnels non-bancaires | D6: 1163100 | E6: 24.1% | G6: BEAC
A7: 2026-03 | B7: CEMAC | C7: Personnes physiques | D7: 405800 | E7: 8.4% | G7: BEAC
A8: 2026-03 | B8: CEMAC | C8: Autres | D8: 313900 | E8: 6.5% | G8: BEAC
A9: → TOTAL | D9: =SUM(D4:D8) -> 0 | E9: =100% -> 1

Sheet DOCUMENTS_META
A1: MÉTADONNÉES DES DOCUMENTS — Règlementation & Publications
A2: Les fichiers sont dans le dossier Documentation/ — chemin relatif à renseigner
A3: Titre | B3: Catégorie | C3: Sous-catégorie | D3: Référence | E3: Date Publication | F3: Auteur / Émetteur | G3: Accès (Public/Restreint) | H3: Chemin Fichier | I3: Taille | J3: Version | K3: Actif | L3: Remarque
A4: Règlement n°03/19/CEMAC/UMAC/CM — Émission des valeurs du Trésor | B4: Réglementation | C4: Règlement | D4: CEMAC/UMAC/CM | E4: 2024-01-15 | F4: CEMAC/UMAC | G4: Public | H4: Documentation\reglementation\reglement cemac relatif au marche des valeurs du tresor (1).pdf | I4: 2.4 Mo | J4: v1.0 | K4: Oui
A5: Instruction n°03/23 — Procédures d'adjudication | B5: Réglementation | C5: Instruction | D5: BEAC/CRCT/003/2023 | E5: 2023-07-10 | F5: BEAC/CRCT | G5: Public | H5: Documentation/reglementation/instruction_03_2023.pdf | I5: 1.8 Mo | J5: v1.0 | K5: Oui
A6: Statistiques Mensuelles du Marché des Valeurs du Trésor de la CEMAC février 2026 | B6: Publication | C6: Bulletin | D6: BUL-T1-2026 | E6: 2026-04-01 | F6: BEAC/CRCT | G6: Public | H6: Documentation\publication\Statistiques Mensuelles du Marché des Valeurs du Trésor de la CEMAC février 2026.pdf | I6: 3.2 Mo | J6: v1.0 | K6: Oui
A7: Rapport annuel marché 2025 | B7: Publication | C7: Rapport annuel | D7: RA-2025 | E7: 2026-02-28 | F7: BEAC/CRCT | G7: Public | H7: Documentation/publication/rapport_annuel_2025.pdf | I7: 8.5 Mo | J7: v1.0 | K7: Oui
A8: Résultats adjudications 2025 — données détaillées | B8: Statistiques | C8: Données marché | D8: STAT-ADJ-2025 | E8: 2026-01-15 | F8: BEAC/CRCT | G8: Restreint | H8: Documentation/publication/adj_data_2025.xlsx | I8: 1.1 Mo | J8: v1.0 | K8: Oui

Sheet ALERTES_ABONNEMENTS
A1: ALERTES & ABONNEMENTS UTILISATEURS
A3: Username | B3: Email Notification | C3: Pays Suivis | D3: Instruments | E3: Taux Min (%) | F3: Maturités | G3: Newsletter | H3: Alerte Emission | I3: Alerte Résultat | J3: Statut Alerte | K3: Date Config

Sheet PARAMETRES
A1: PARAMÈTRES GLOBAUX DE LA PLATEFORME
A2: Paramètre | B2: Valeur | C2: Description
A3: nom_plateforme | B3: CTDAM-CEMAC | C3: Nom affiché sur la plateforme
A4: version | B4: 1.0 | C4: Version actuelle
A5: email_contact | B5: crct@beac.int | C5: Email de contact BEAC/CRCT
A6: telephone | B6: + 237 222 23 40 30 | C6: Téléphone BEAC
A7: adresse | B7: Avenue Monseigneur Vogt, Yaoundé | C7: Adresse BEAC
A8: session_duree_heures | B8: 8 | C8: Durée de session (heures)
A9: delai_validation_jours | B9: 5 | C9: Délai de validation des comptes (jours ouvrés)
A10: monnaie | B10: XAF | C10: Devise utilisée
A11: zone | B11: CEMAC | C11: Zone géographique couverte
A12: pays_membres | B12: CMR,GAB,COG,RCA,GNQ,TCD | C12: Codes pays membres
A13: instruments_disponibles | B13: BTA,OTA | C13: Instruments gérés
A14: maturites_bta | B14: 13s,26s,52s | C14: Maturités BTA (semaines)
A15: maturites_ota | B15: 2a,3a,5a,7a,10a,15a | C15: Maturités OTA (années)
A16: dossier_documentation | B16: Documentation/ | C16: Chemin dossier docs
A17: dossier_reglementation | B17: Documentation/reglementation/ | C17: Chemin réglementation
A18: dossier_publications | B18: Documentation/publication/ | C18: Chemin publications
A19: taux_inflation_reference | B19: Valeur en PAYS_MACRO | C19: Source inflation
A20: refresh_encours | B20: Mensuel | C20: Fréquence mise à jour encours
A21: refresh_courbe_taux | B21: Après chaque adjudication | C21: Fréquence mise à jour courbe taux

Sheet KPIs_ACCUEIL
A1: CHIFFRES CLÉS DE LA PAGE D'ACCUEIL — Alimentés automatiquement
A2: Ces cellules contiennent des formules qui lisent EMISSIONS, ENCOURS_MENSUEL, SVT, COURBE_TAUX
A3: KPI | B3: Formule / Source | C3: Valeur Calculée | D3: Unité | E3: Onglet Affiché
A4: Encours Global | B4: =SUMIF(ENCOURS_MENSUEL!C:C,MAX(ENCOURS_MENSUEL!C:C),ENCOURS_MENSUEL!F:F) -> 0 | D4: M XAF | E4: Accueil
A5: Nb SVT Actifs | B5: =COUNTIF(SVT!G:G,"Actif") -> 3 | D5: Nombre | E5: Accueil
A6: Nb Adjudications (12 mois) | B6: =COUNTIFS(EMISSIONS!G:G,">="&DATE(YEAR(TODAY())-1,MONTH(TODAY()),DAY(TODAY()))) -> 561 | D6: Nombre | E6: Accueil
A7: Volumes Émis (12 mois) | B7: =SUMIFS(EMISSIONS!F:F,EMISSIONS!G:G,">="&DATE(YEAR(TODAY())-1,MONTH(TODAY()),DAY(TODAY()))) -> 8370430.9 | D7: M XAF | E7: Accueil
A8: Taux Couverture Moyen | B8: =AVERAGEIF(EMISSIONS!W:W,"Résultat publié",EMISSIONS!V:V) -> #DIV/0! | D8: x | E8: Accueil
A9: Dernier Taux BTA 13s | B9: =INDEX(COURBE_TAUX!D:D,MATCH(MAX(COURBE_TAUX!A:A),COURBE_TAUX!A:A,0)) -> #N/A | D9: % | E9: Accueil
A10: Nb Codes ISIN Actifs | B10: =COUNTA(EMISSIONS!A:A)-1 -> 3350 | D10: Nombre | E10: Accueil
A11: Nb Pays Émetteurs | B11: =COUNTIF(PAYS_MACRO!C:C,MAX(PAYS_MACRO!C:C)) -> 6 | D11: 6 | E11: Accueil
